{
  "version": "0.13.75",
  "description": "maxx",
  "homepage": "https://github.com/awsl-project/maxx",
  "license": "MIT",
  "architecture": {
    "64bit": {
      "url": "https://github.com/awsl-project/maxx/releases/download/v0.13.75/maxx.exe",
      "hash": "8ae75b047a57f578d171e1f14e86865febf44a9db9cc0f1c194fc13da5ebca75"
    }
  },
  "bin": "maxx.exe",
  "checkver": {
    "github": "https://github.com/awsl-project/maxx"
  },
  "autoupdate": {
    "architecture": {
      "64bit": {
        "url": "https://github.com/awsl-project/maxx/releases/download/v$version/maxx.exe"
      }
    }
  }
}
